{
  "b": 209,
  "disableInputWhenNotFocused": true,
  "mangledName": "Lvl1Map",
  "name": "Lvl1Map",
  "oglFOV": 90,
  "oglZFar": 500,
  "oglZNear": 1,
  "r": 209,
  "standardSortMethod": true,
  "stopSoundsOnStartup": true,
  "title": "",
  "v": 209,
  "uiSettings": {
    "grid": false,
    "gridB": 255,
    "gridG": 180,
    "gridHeight": 32,
    "gridOffsetX": 0,
    "gridOffsetY": 0,
    "gridR": 158,
    "gridWidth": 32,
    "snap": false,
    "windowMask": false,
    "zoomFactor": 0.8364
  },
  "objectsGroups": [
    {
      "name": "Group",
      "objects": []
    }
  ],
  "variables": [],
  "instances": [
    {
      "angle": 0,
      "customSize": true,
      "height": 808,
      "layer": "",
      "locked": true,
      "name": "Background",
      "width": 3599,
      "x": -116,
      "y": -149,
      "zOrder": 1,
      "numberProperties": [],
      "stringProperties": [],
      "initialVariables": []
    },
    {
      "angle": 0,
      "customSize": true,
      "height": 125,
      "layer": "",
      "locked": false,
      "name": "SquareSurface",
      "width": 274,
      "x": -116,
      "y": 475,
      "zOrder": 2,
      "numberProperties": [],
      "stringProperties": [],
      "initialVariables": []
    },
    {
      "angle": 0,
      "customSize": true,
      "height": 58,
      "layer": "",
      "locked": false,
      "name": "SquareSurface",
      "width": 291,
      "x": 158,
      "y": 542,
      "zOrder": 4,
      "numberProperties": [],
      "stringProperties": [],
      "initialVariables": []
    },
    {
      "angle": 0,
      "customSize": true,
      "height": 79,
      "layer": "",
      "locked": false,
      "name": "Player",
      "width": 107,
      "x": 34,
      "y": 47,
      "zOrder": 5,
      "numberProperties": [],
      "stringProperties": [],
      "initialVariables": []
    },
    {
      "angle": 0,
      "customSize": true,
      "height": 58,
      "layer": "",
      "locked": false,
      "name": "SquareSurface",
      "width": 291,
      "x": 158,
      "y": 542,
      "zOrder": 4,
      "numberProperties": [],
      "stringProperties": [],
      "initialVariables": []
    },
    {
      "angle": 0,
      "customSize": true,
      "height": 67,
      "layer": "",
      "locked": false,
      "name": "LeftCliff",
      "width": 80,
      "x": 198,
      "y": 388,
      "zOrder": 6,
      "numberProperties": [],
      "stringProperties": [],
      "initialVariables": []
    },
    {
      "angle": 0,
      "customSize": true,
      "height": 63,
      "layer": "",
      "locked": false,
      "name": "OceanSurface",
      "width": 179,
      "x": 449,
      "y": 537,
      "zOrder": 7,
      "numberProperties": [],
      "stringProperties": [],
      "initialVariables": []
    },
    {
      "angle": 0,
      "customSize": true,
      "height": 58,
      "layer": "",
      "locked": false,
      "name": "SquareSurface",
      "width": 287,
      "x": 629,
      "y": 542,
      "zOrder": 4,
      "numberProperties": [],
      "stringProperties": [],
      "initialVariables": []
    },
    {
      "angle": 0,
      "customSize": true,
      "height": 58,
      "layer": "",
      "locked": false,
      "name": "RightCurveSurface",
      "width": 127,
      "x": 915,
      "y": 542,
      "zOrder": 8,
      "numberProperties": [],
      "stringProperties": [],
      "initialVariables": []
    },
    {
      "angle": 0,
      "customSize": false,
      "height": 0,
      "layer": "",
      "locked": false,
      "name": "NewObject5",
      "width": 0,
      "x": 1042,
      "y": 414,
      "zOrder": 9,
      "numberProperties": [],
      "stringProperties": [],
      "initialVariables": []
    },
    {
      "angle": 0,
      "customSize": true,
      "height": 58,
      "layer": "",
      "locked": false,
      "name": "NewObject6",
      "width": 70,
      "x": 1041,
      "y": 542,
      "zOrder": 10,
      "numberProperties": [],
      "stringProperties": [],
      "initialVariables": []
    },
    {
      "angle": 0,
      "customSize": true,
      "height": 59,
      "layer": "",
      "locked": false,
      "name": "NewObject7",
      "width": 208,
      "x": 1111,
      "y": 541,
      "zOrder": 11,
      "numberProperties": [],
      "stringProperties": [],
      "initialVariables": []
    },
    {
      "angle": 0,
      "customSize": true,
      "height": 127,
      "layer": "",
      "locked": false,
      "name": "NewObject8",
      "width": 182,
      "x": 1170,
      "y": 414,
      "zOrder": 3,
      "numberProperties": [],
      "stringProperties": [],
      "initialVariables": []
    },
    {
      "angle": 0,
      "customSize": true,
      "height": 59,
      "layer": "",
      "locked": false,
      "name": "SurfaceLeftCurve",
      "width": 128,
      "x": 1448,
      "y": 541,
      "zOrder": 13,
      "numberProperties": [],
      "stringProperties": [],
      "initialVariables": []
    },
    {
      "angle": 0,
      "customSize": true,
      "height": 59,
      "layer": "",
      "locked": false,
      "name": "SoilRight",
      "width": 129,
      "x": 1319,
      "y": 541,
      "zOrder": 14,
      "numberProperties": [],
      "stringProperties": [],
      "initialVariables": []
    },
    {
      "angle": 0,
      "customSize": true,
      "height": 127,
      "layer": "",
      "locked": false,
      "name": "SurfaceRightCrumble",
      "width": 128,
      "x": 1319,
      "y": 414,
      "zOrder": 2,
      "numberProperties": [],
      "stringProperties": [],
      "initialVariables": []
    },
    {
      "angle": 0,
      "customSize": true,
      "height": 487.462,
      "layer": "",
      "locked": false,
      "name": "TiledCastlePlatform",
      "width": 502.923,
      "x": -254.787,
      "y": 139.704,
      "zOrder": 1,
      "numberProperties": [],
      "stringProperties": [],
      "initialVariables": []
    },
    {
      "angle": 0,
      "customSize": true,
      "height": 74,
      "layer": "",
      "locked": false,
      "name": "PlayerHitBox",
      "width": 32,
      "x": 42,
      "y": 47,
      "zOrder": 2,
      "numberProperties": [],
      "stringProperties": [],
      "initialVariables": []
    },
    {
      "angle": 0,
      "customSize": true,
      "height": 67,
      "layer": "",
      "locked": false,
      "name": "CliffRight",
      "width": 80,
      "x": 278,
      "y": 388,
      "zOrder": 18,
      "numberProperties": [],
      "stringProperties": [],
      "initialVariables": []
    },
    {
      "angle": 0,
      "customSize": true,
      "height": 50,
      "layer": "",
      "locked": false,
      "name": "CliffRight",
      "width": 59,
      "x": 525,
      "y": 330,
      "zOrder": 19,
      "numberProperties": [],
      "stringProperties": [],
      "initialVariables": []
    },
    {
      "angle": 0,
      "customSize": true,
      "height": 50,
      "layer": "",
      "locked": false,
      "name": "LeftCliff",
      "width": 58,
      "x": 467,
      "y": 330,
      "zOrder": 20,
      "numberProperties": [],
      "stringProperties": [],
      "initialVariables": []
    },
    {
      "angle": 0,
      "customSize": true,
      "height": 52,
      "layer": "",
      "locked": false,
      "name": "CliffRight",
      "width": 60,
      "x": 1291,
      "y": 239,
      "zOrder": 21,
      "numberProperties": [],
      "stringProperties": [],
      "initialVariables": []
    },
    {
      "angle": 0,
      "customSize": true,
      "height": 52,
      "layer": "",
      "locked": false,
      "name": "LeftCliff",
      "width": 68,
      "x": 1137,
      "y": 239,
      "zOrder": 22,
      "numberProperties": [],
      "stringProperties": [],
      "initialVariables": []
    },
    {
      "angle": 0,
      "customSize": true,
      "height": 52,
      "layer": "",
      "locked": false,
      "name": "CliffMiddle",
      "width": 86,
      "x": 1205,
      "y": 239,
      "zOrder": 23,
      "numberProperties": [],
      "stringProperties": [],
      "initialVariables": []
    },
    {
      "angle": 0,
      "customSize": true,
      "height": 52,
      "layer": "",
      "locked": false,
      "name": "Box",
      "width": 47,
      "x": 905,
      "y": 492,
      "zOrder": 24,
      "numberProperties": [],
      "stringProperties": [],
      "initialVariables": []
    },
    {
      "angle": 0,
      "customSize": true,
      "height": 59,
      "layer": "",
      "locked": false,
      "name": "NewObject8",
      "width": 550,
      "x": 1571,
      "y": 541,
      "zOrder": 25,
      "numberProperties": [],
      "stringProperties": [],
      "initialVariables": []
    },
    {
      "angle": 0,
      "customSize": false,
      "height": 0,
      "layer": "",
      "locked": false,
      "name": "NewObject5",
      "width": 0,
      "x": 2243,
      "y": 413,
      "zOrder": 9,
      "numberProperties": [],
      "stringProperties": [],
      "initialVariables": []
    },
    {
      "angle": 0,
      "customSize": true,
      "height": 58,
      "layer": "",
      "locked": false,
      "name": "NewObject6",
      "width": 70,
      "x": 2242,
      "y": 541,
      "zOrder": 10,
      "numberProperties": [],
      "stringProperties": [],
      "initialVariables": []
    },
    {
      "angle": 0,
      "customSize": true,
      "height": 59,
      "layer": "",
      "locked": false,
      "name": "NewObject7",
      "width": 208,
      "x": 2312,
      "y": 540,
      "zOrder": 11,
      "numberProperties": [],
      "stringProperties": [],
      "initialVariables": []
    },
    {
      "angle": 0,
      "customSize": true,
      "height": 127,
      "layer": "",
      "locked": false,
      "name": "NewObject8",
      "width": 182,
      "x": 2371,
      "y": 413,
      "zOrder": 3,
      "numberProperties": [],
      "stringProperties": [],
      "initialVariables": []
    },
    {
      "angle": 0,
      "customSize": true,
      "height": 59,
      "layer": "",
      "locked": false,
      "name": "SoilRight",
      "width": 124,
      "x": 2520,
      "y": 540,
      "zOrder": 5,
      "numberProperties": [],
      "stringProperties": [],
      "initialVariables": []
    },
    {
      "angle": 0,
      "customSize": true,
      "height": 127,
      "layer": "",
      "locked": false,
      "name": "SurfaceRightCrumble",
      "width": 124,
      "x": 2520,
      "y": 413,
      "zOrder": 5,
      "numberProperties": [],
      "stringProperties": [],
      "initialVariables": []
    },
    {
      "angle": 0,
      "customSize": true,
      "height": 58,
      "layer": "",
      "locked": false,
      "name": "RightCurveSurface",
      "width": 127,
      "x": 2116,
      "y": 541,
      "zOrder": 8,
      "numberProperties": [],
      "stringProperties": [],
      "initialVariables": []
    },
    {
      "angle": 0,
      "customSize": true,
      "height": 93,
      "layer": "",
      "locked": false,
      "name": "OceanSurface",
      "width": 459,
      "x": 2640,
      "y": 435,
      "zOrder": 4,
      "numberProperties": [],
      "stringProperties": [],
      "initialVariables": []
    },
    {
      "angle": 0,
      "customSize": true,
      "height": 74,
      "layer": "",
      "locked": false,
      "name": "water",
      "width": 456,
      "x": 2638,
      "y": 526,
      "zOrder": 4,
      "numberProperties": [],
      "stringProperties": [],
      "initialVariables": []
    },
    {
      "angle": 0,
      "customSize": false,
      "height": 0,
      "layer": "",
      "locked": false,
      "name": "NewObject5",
      "width": 0,
      "x": 3085,
      "y": 413,
      "zOrder": 9,
      "numberProperties": [],
      "stringProperties": [],
      "initialVariables": []
    },
    {
      "angle": 0,
      "customSize": true,
      "height": 58,
      "layer": "",
      "locked": false,
      "name": "NewObject6",
      "width": 70,
      "x": 3084,
      "y": 541,
      "zOrder": 10,
      "numberProperties": [],
      "stringProperties": [],
      "initialVariables": []
    },
    {
      "angle": 0,
      "customSize": true,
      "height": 59,
      "layer": "",
      "locked": false,
      "name": "NewObject7",
      "width": 208,
      "x": 3154,
      "y": 540,
      "zOrder": 11,
      "numberProperties": [],
      "stringProperties": [],
      "initialVariables": []
    },
    {
      "angle": 0,
      "customSize": true,
      "height": 127,
      "layer": "",
      "locked": false,
      "name": "NewObject8",
      "width": 182,
      "x": 3213,
      "y": 413,
      "zOrder": 3,
      "numberProperties": [],
      "stringProperties": [],
      "initialVariables": []
    },
    {
      "angle": 0,
      "customSize": true,
      "height": 59,
      "layer": "",
      "locked": false,
      "name": "SoilRight",
      "width": 129,
      "x": 3362,
      "y": 540,
      "zOrder": 14,
      "numberProperties": [],
      "stringProperties": [],
      "initialVariables": []
    },
    {
      "angle": 0,
      "customSize": true,
      "height": 127,
      "layer": "",
      "locked": false,
      "name": "SurfaceRightCrumble",
      "width": 128,
      "x": 3362,
      "y": 413,
      "zOrder": 4,
      "numberProperties": [],
      "stringProperties": [],
      "initialVariables": []
    },
    {
      "angle": 0,
      "customSize": true,
      "height": 52,
      "layer": "",
      "locked": false,
      "name": "CliffRight",
      "width": 60,
      "x": 2128,
      "y": 462,
      "zOrder": 21,
      "numberProperties": [],
      "stringProperties": [],
      "initialVariables": []
    },
    {
      "angle": 0,
      "customSize": true,
      "height": 52,
      "layer": "",
      "locked": false,
      "name": "LeftCliff",
      "width": 68,
      "x": 1974,
      "y": 462,
      "zOrder": 22,
      "numberProperties": [],
      "stringProperties": [],
      "initialVariables": []
    },
    {
      "angle": 0,
      "customSize": true,
      "height": 52,
      "layer": "",
      "locked": false,
      "name": "CliffMiddle",
      "width": 86,
      "x": 2042,
      "y": 462,
      "zOrder": 23,
      "numberProperties": [],
      "stringProperties": [],
      "initialVariables": []
    },
    {
      "angle": 0,
      "customSize": true,
      "height": 52,
      "layer": "",
      "locked": false,
      "name": "CliffRight",
      "width": 60,
      "x": 2829,
      "y": 321,
      "zOrder": 2,
      "numberProperties": [],
      "stringProperties": [],
      "initialVariables": []
    },
    {
      "angle": 0,
      "customSize": true,
      "height": 52,
      "layer": "",
      "locked": false,
      "name": "LeftCliff",
      "width": 68,
      "x": 2675,
      "y": 321,
      "zOrder": 2,
      "numberProperties": [],
      "stringProperties": [],
      "initialVariables": []
    },
    {
      "angle": 0,
      "customSize": true,
      "height": 52,
      "layer": "",
      "locked": false,
      "name": "CliffMiddle",
      "width": 86,
      "x": 2743,
      "y": 321,
      "zOrder": 2,
      "numberProperties": [],
      "stringProperties": [],
      "initialVariables": []
    },
    {
      "angle": 0,
      "customSize": true,
      "height": 52,
      "layer": "",
      "locked": false,
      "name": "CliffRight",
      "width": 60,
      "x": 3056.61,
      "y": 260.512,
      "zOrder": 21,
      "numberProperties": [],
      "stringProperties": [],
      "initialVariables": []
    },
    {
      "angle": 0,
      "customSize": true,
      "height": 52,
      "layer": "",
      "locked": false,
      "name": "LeftCliff",
      "width": 68,
      "x": 2902.61,
      "y": 260.512,
      "zOrder": 22,
      "numberProperties": [],
      "stringProperties": [],
      "initialVariables": []
    },
    {
      "angle": 0,
      "customSize": true,
      "height": 52,
      "layer": "",
      "locked": false,
      "name": "CliffMiddle",
      "width": 86,
      "x": 2970.61,
      "y": 260.512,
      "zOrder": 23,
      "numberProperties": [],
      "stringProperties": [],
      "initialVariables": []
    },
    {
      "angle": 0,
      "customSize": true,
      "height": 173,
      "layer": "",
      "locked": false,
      "name": "tree2",
      "width": 172,
      "x": 1163,
      "y": 63,
      "zOrder": 2,
      "numberProperties": [],
      "stringProperties": [],
      "initialVariables": []
    },
    {
      "angle": 0,
      "customSize": true,
      "height": 190,
      "layer": "",
      "locked": false,
      "name": "tree3",
      "width": 139,
      "x": 205,
      "y": 200,
      "zOrder": 2,
      "numberProperties": [],
      "stringProperties": [],
      "initialVariables": []
    },
    {
      "angle": 0,
      "customSize": true,
      "height": 14,
      "layer": "",
      "locked": false,
      "name": "stone",
      "width": 36,
      "x": 279,
      "y": 376,
      "zOrder": 3,
      "numberProperties": [],
      "stringProperties": [],
      "initialVariables": []
    },
    {
      "angle": 0,
      "customSize": true,
      "height": 13,
      "layer": "",
      "locked": false,
      "name": "stone",
      "width": 24,
      "x": 753,
      "y": 532,
      "zOrder": 29,
      "numberProperties": [],
      "stringProperties": [],
      "initialVariables": []
    },
    {
      "angle": 0,
      "customSize": false,
      "height": 0,
      "layer": "",
      "locked": false,
      "name": "mushroom1",
      "width": 0,
      "x": 1748,
      "y": 508,
      "zOrder": 3,
      "numberProperties": [],
      "stringProperties": [],
      "initialVariables": []
    },
    {
      "angle": 0,
      "customSize": false,
      "height": 0,
      "layer": "",
      "locked": false,
      "name": "mushroom2",
      "width": 0,
      "x": 2021,
      "y": 432,
      "zOrder": 3,
      "numberProperties": [],
      "stringProperties": [],
      "initialVariables": []
    },
    {
      "angle": 0,
      "customSize": false,
      "height": 0,
      "layer": "",
      "locked": false,
      "name": "bush1",
      "width": 0,
      "x": 1480,
      "y": 486,
      "zOrder": 32,
      "numberProperties": [],
      "stringProperties": [],
      "initialVariables": []
    },
    {
      "angle": 0,
      "customSize": true,
      "height": 271,
      "layer": "",
      "locked": false,
      "name": "Ladder",
      "width": 72,
      "x": 2831,
      "y": 331,
      "zOrder": 3,
      "numberProperties": [],
      "stringProperties": [],
      "initialVariables": []
    },
    {
      "angle": 0,
      "customSize": false,
      "height": 0,
      "layer": "",
      "locked": false,
      "name": "tree1",
      "width": 0,
      "x": 3181,
      "y": 373,
      "zOrder": 33,
      "numberProperties": [],
      "stringProperties": [],
      "initialVariables": []
    },
    {
      "angle": 0,
      "customSize": true,
      "height": 32,
      "layer": "",
      "locked": false,
      "name": "Platform",
      "width": 319,
      "x": 3161,
      "y": 182,
      "zOrder": 34,
      "numberProperties": [],
      "stringProperties": [],
      "initialVariables": []
    },
    {
      "angle": 0,
      "customSize": true,
      "height": 32,
      "layer": "",
      "locked": false,
      "name": "Platform",
      "width": 79,
      "x": 729,
      "y": 329,
      "zOrder": 35,
      "numberProperties": [],
      "stringProperties": [],
      "initialVariables": []
    },
    {
      "angle": 0,
      "customSize": true,
      "height": 32,
      "layer": "",
      "locked": false,
      "name": "Platform",
      "width": 79,
      "x": 888,
      "y": 267,
      "zOrder": 35,
      "numberProperties": [],
      "stringProperties": [],
      "initialVariables": []
    },
    {
      "angle": 0,
      "customSize": true,
      "height": 32,
      "layer": "",
      "locked": false,
      "name": "Platform",
      "width": 79,
      "x": 1002,
      "y": 177,
      "zOrder": 35,
      "numberProperties": [],
      "stringProperties": [],
      "initialVariables": []
    }
  ],
  "objects": [
    {
      "name": "Player",
      "tags": "",
      "type": "Sprite",
      "updateIfNotVisible": false,
      "variables": [],
      "behaviors": [],
      "animations": [
        {
          "name": "idle",
          "useMultipleDirections": false,
          "directions": [
            {
              "looping": true,
              "timeBetweenFrames": 0.08,
              "sprites": [
                {
                  "hasCustomCollisionMask": true,
                  "image": "flatboy/png/Idle (1).png",
                  "points": [],
                  "originPoint": {
                    "name": "origine",
                    "x": 2.5,
                    "y": -1
                  },
                  "centerPoint": {
                    "automatic": false,
                    "name": "centre",
                    "x": 143.281,
                    "y": 337.5
                  },
                  "customCollisionMask": []
                },
                {
                  "hasCustomCollisionMask": true,
                  "image": "flatboy/png/Idle (2).png",
                  "points": [],
                  "originPoint": {
                    "name": "origine",
                    "x": 2.5,
                    "y": -1
                  },
                  "centerPoint": {
                    "automatic": false,
                    "name": "centre",
                    "x": 143.281,
                    "y": 337.5
                  },
                  "customCollisionMask": []
                },
                {
                  "hasCustomCollisionMask": true,
                  "image": "flatboy/png/Idle (3).png",
                  "points": [],
                  "originPoint": {
                    "name": "origine",
                    "x": 2.5,
                    "y": -1
                  },
                  "centerPoint": {
                    "automatic": false,
                    "name": "centre",
                    "x": 143.281,
                    "y": 337.5
                  },
                  "customCollisionMask": []
                },
                {
                  "hasCustomCollisionMask": true,
                  "image": "flatboy/png/Idle (4).png",
                  "points": [],
                  "originPoint": {
                    "name": "origine",
                    "x": 2.5,
                    "y": -1
                  },
                  "centerPoint": {
                    "automatic": false,
                    "name": "centre",
                    "x": 143.281,
                    "y": 337.5
                  },
                  "customCollisionMask": []
                },
                {
                  "hasCustomCollisionMask": true,
                  "image": "flatboy/png/Idle (5).png",
                  "points": [],
                  "originPoint": {
                    "name": "origine",
                    "x": 2.5,
                    "y": -1
                  },
                  "centerPoint": {
                    "automatic": false,
                    "name": "centre",
                    "x": 143.281,
                    "y": 337.5
                  },
                  "customCollisionMask": []
                },
                {
                  "hasCustomCollisionMask": true,
                  "image": "flatboy/png/Idle (6).png",
                  "points": [],
                  "originPoint": {
                    "name": "origine",
                    "x": 2.5,
                    "y": -1
                  },
                  "centerPoint": {
                    "automatic": false,
                    "name": "centre",
                    "x": 143.281,
                    "y": 337.5
                  },
                  "customCollisionMask": []
                },
                {
                  "hasCustomCollisionMask": true,
                  "image": "flatboy/png/Idle (7).png",
                  "points": [],
                  "originPoint": {
                    "name": "origine",
                    "x": 2.5,
                    "y": -1
                  },
                  "centerPoint": {
                    "automatic": false,
                    "name": "centre",
                    "x": 143.281,
                    "y": 337.5
                  },
                  "customCollisionMask": []
                },
                {
                  "hasCustomCollisionMask": true,
                  "image": "flatboy/png/Idle (8).png",
                  "points": [],
                  "originPoint": {
                    "name": "origine",
                    "x": 2.5,
                    "y": -1
                  },
                  "centerPoint": {
                    "automatic": false,
                    "name": "centre",
                    "x": 143.281,
                    "y": 337.5
                  },
                  "customCollisionMask": []
                },
                {
                  "hasCustomCollisionMask": true,
                  "image": "flatboy/png/Idle (9).png",
                  "points": [],
                  "originPoint": {
                    "name": "origine",
                    "x": 2.5,
                    "y": -1
                  },
                  "centerPoint": {
                    "automatic": false,
                    "name": "centre",
                    "x": 143.281,
                    "y": 337.5
                  },
                  "customCollisionMask": []
                },
                {
                  "hasCustomCollisionMask": true,
                  "image": "flatboy/png/Idle (10).png",
                  "points": [],
                  "originPoint": {
                    "name": "origine",
                    "x": 2.5,
                    "y": -1
                  },
                  "centerPoint": {
                    "automatic": false,
                    "name": "centre",
                    "x": 143.281,
                    "y": 337.5
                  },
                  "customCollisionMask": []
                },
                {
                  "hasCustomCollisionMask": true,
                  "image": "flatboy/png/Idle (11).png",
                  "points": [],
                  "originPoint": {
                    "name": "origine",
                    "x": 2.5,
                    "y": -1
                  },
                  "centerPoint": {
                    "automatic": false,
                    "name": "centre",
                    "x": 143.281,
                    "y": 337.5
                  },
                  "customCollisionMask": []
                },
                {
                  "hasCustomCollisionMask": true,
                  "image": "flatboy/png/Idle (12).png",
                  "points": [],
                  "originPoint": {
                    "name": "origine",
                    "x": 2.5,
                    "y": -1
                  },
                  "centerPoint": {
                    "automatic": false,
                    "name": "centre",
                    "x": 143.281,
                    "y": 337.5
                  },
                  "customCollisionMask": []
                },
                {
                  "hasCustomCollisionMask": true,
                  "image": "flatboy/png/Idle (13).png",
                  "points": [],
                  "originPoint": {
                    "name": "origine",
                    "x": 2.5,
                    "y": -1
                  },
                  "centerPoint": {
                    "automatic": false,
                    "name": "centre",
                    "x": 143.281,
                    "y": 337.5
                  },
                  "customCollisionMask": []
                },
                {
                  "hasCustomCollisionMask": true,
                  "image": "flatboy/png/Idle (14).png",
                  "points": [],
                  "originPoint": {
                    "name": "origine",
                    "x": 2.5,
                    "y": -1
                  },
                  "centerPoint": {
                    "automatic": false,
                    "name": "centre",
                    "x": 143.281,
                    "y": 337.5
                  },
                  "customCollisionMask": []
                },
                {
                  "hasCustomCollisionMask": true,
                  "image": "flatboy/png/Idle (15).png",
                  "points": [],
                  "originPoint": {
                    "name": "origine",
                    "x": 2.5,
                    "y": -1
                  },
                  "centerPoint": {
                    "automatic": false,
                    "name": "centre",
                    "x": 143.281,
                    "y": 337.5
                  },
                  "customCollisionMask": []
                }
              ]
            }
          ]
        },
        {
          "name": "dead ",
          "useMultipleDirections": false,
          "directions": [
            {
              "looping": false,
              "timeBetweenFrames": 0.05,
              "sprites": [
                {
                  "hasCustomCollisionMask": true,
                  "image": "flatboy/png/Dead (1).png",
                  "points": [],
                  "originPoint": {
                    "name": "origine",
                    "x": 2.5,
                    "y": -1
                  },
                  "centerPoint": {
                    "automatic": false,
                    "name": "centre",
                    "x": 143.281,
                    "y": 337.5
                  },
                  "customCollisionMask": []
                },
                {
                  "hasCustomCollisionMask": true,
                  "image": "flatboy/png/Dead (2).png",
                  "points": [],
                  "originPoint": {
                    "name": "origine",
                    "x": 2.5,
                    "y": -1
                  },
                  "centerPoint": {
                    "automatic": false,
                    "name": "centre",
                    "x": 143.281,
                    "y": 337.5
                  },
                  "customCollisionMask": []
                },
                {
                  "hasCustomCollisionMask": true,
                  "image": "flatboy/png/Dead (3).png",
                  "points": [],
                  "originPoint": {
                    "name": "origine",
                    "x": 2.5,
                    "y": -1
                  },
                  "centerPoint": {
                    "automatic": false,
                    "name": "centre",
                    "x": 143.281,
                    "y": 337.5
                  },
                  "customCollisionMask": []
                },
                {
                  "hasCustomCollisionMask": true,
                  "image": "flatboy/png/Dead (4).png",
                  "points": [],
                  "originPoint": {
                    "name": "origine",
                    "x": 2.5,
                    "y": -1
                  },
                  "centerPoint": {
                    "automatic": false,
                    "name": "centre",
                    "x": 143.281,
                    "y": 337.5
                  },
                  "customCollisionMask": []
                },
                {
                  "hasCustomCollisionMask": true,
                  "image": "flatboy/png/Dead (5).png",
                  "points": [],
                  "originPoint": {
                    "name": "origine",
                    "x": 2.5,
                    "y": -1
                  },
                  "centerPoint": {
                    "automatic": false,
                    "name": "centre",
                    "x": 143.281,
                    "y": 337.5
                  },
                  "customCollisionMask": []
                },
                {
                  "hasCustomCollisionMask": true,
                  "image": "flatboy/png/Dead (6).png",
                  "points": [],
                  "originPoint": {
                    "name": "origine",
                    "x": 2.5,
                    "y": -1
                  },
                  "centerPoint": {
                    "automatic": false,
                    "name": "centre",
                    "x": 143.281,
                    "y": 337.5
                  },
                  "customCollisionMask": []
                },
                {
                  "hasCustomCollisionMask": true,
                  "image": "flatboy/png/Dead (7).png",
                  "points": [],
                  "originPoint": {
                    "name": "origine",
                    "x": 2.5,
                    "y": -1
                  },
                  "centerPoint": {
                    "automatic": false,
                    "name": "centre",
                    "x": 143.281,
                    "y": 337.5
                  },
                  "customCollisionMask": []
                },
                {
                  "hasCustomCollisionMask": true,
                  "image": "flatboy/png/Dead (8).png",
                  "points": [],
                  "originPoint": {
                    "name": "origine",
                    "x": 2.5,
                    "y": -1
                  },
                  "centerPoint": {
                    "automatic": false,
                    "name": "centre",
                    "x": 143.281,
                    "y": 337.5
                  },
                  "customCollisionMask": []
                },
                {
                  "hasCustomCollisionMask": true,
                  "image": "flatboy/png/Dead (9).png",
                  "points": [],
                  "originPoint": {
                    "name": "origine",
                    "x": 2.5,
                    "y": -1
                  },
                  "centerPoint": {
                    "automatic": false,
                    "name": "centre",
                    "x": 143.281,
                    "y": 337.5
                  },
                  "customCollisionMask": []
                },
                {
                  "hasCustomCollisionMask": true,
                  "image": "flatboy/png/Dead (10).png",
                  "points": [],
                  "originPoint": {
                    "name": "origine",
                    "x": 2.5,
                    "y": -1
                  },
                  "centerPoint": {
                    "automatic": false,
                    "name": "centre",
                    "x": 143.281,
                    "y": 337.5
                  },
                  "customCollisionMask": []
                },
                {
                  "hasCustomCollisionMask": true,
                  "image": "flatboy/png/Dead (11).png",
                  "points": [],
                  "originPoint": {
                    "name": "origine",
                    "x": 2.5,
                    "y": -1
                  },
                  "centerPoint": {
                    "automatic": false,
                    "name": "centre",
                    "x": 143.281,
                    "y": 337.5
                  },
                  "customCollisionMask": []
                },
                {
                  "hasCustomCollisionMask": true,
                  "image": "flatboy/png/Dead (12).png",
                  "points": [],
                  "originPoint": {
                    "name": "origine",
                    "x": 2.5,
                    "y": -1
                  },
                  "centerPoint": {
                    "automatic": false,
                    "name": "centre",
                    "x": 143.281,
                    "y": 337.5
                  },
                  "customCollisionMask": []
                },
                {
                  "hasCustomCollisionMask": true,
                  "image": "flatboy/png/Dead (13).png",
                  "points": [],
                  "originPoint": {
                    "name": "origine",
                    "x": 2.5,
                    "y": -1
                  },
                  "centerPoint": {
                    "automatic": false,
                    "name": "centre",
                    "x": 143.281,
                    "y": 337.5
                  },
                  "customCollisionMask": []
                },
                {
                  "hasCustomCollisionMask": true,
                  "image": "flatboy/png/Dead (14).png",
                  "points": [],
                  "originPoint": {
                    "name": "origine",
                    "x": 2.5,
                    "y": -1
                  },
                  "centerPoint": {
                    "automatic": false,
                    "name": "centre",
                    "x": 143.281,
                    "y": 337.5
                  },
                  "customCollisionMask": []
                },
                {
                  "hasCustomCollisionMask": true,
                  "image": "flatboy/png/Dead (15).png",
                  "points": [],
                  "originPoint": {
                    "name": "origine",
                    "x": 2.5,
                    "y": -1
                  },
                  "centerPoint": {
                    "automatic": false,
                    "name": "centre",
                    "x": 143.281,
                    "y": 337.5
                  },
                  "customCollisionMask": []
                }
              ]
            }
          ]
        },
        {
          "name": "jumping",
          "useMultipleDirections": false,
          "directions": [
            {
              "looping": false,
              "timeBetweenFrames": 0.08,
              "sprites": [
                {
                  "hasCustomCollisionMask": true,
                  "image": "flatboy/png/Jump (1).png",
                  "points": [],
                  "originPoint": {
                    "name": "origine",
                    "x": 2.5,
                    "y": -1
                  },
                  "centerPoint": {
                    "automatic": false,
                    "name": "centre",
                    "x": 143.281,
                    "y": 337.5
                  },
                  "customCollisionMask": []
                },
                {
                  "hasCustomCollisionMask": true,
                  "image": "flatboy/png/Jump (2).png",
                  "points": [],
                  "originPoint": {
                    "name": "origine",
                    "x": 2.5,
                    "y": -1
                  },
                  "centerPoint": {
                    "automatic": false,
                    "name": "centre",
                    "x": 143.281,
                    "y": 337.5
                  },
                  "customCollisionMask": []
                },
                {
                  "hasCustomCollisionMask": true,
                  "image": "flatboy/png/Jump (3).png",
                  "points": [],
                  "originPoint": {
                    "name": "origine",
                    "x": 2.5,
                    "y": -1
                  },
                  "centerPoint": {
                    "automatic": false,
                    "name": "centre",
                    "x": 143.281,
                    "y": 337.5
                  },
                  "customCollisionMask": []
                },
                {
                  "hasCustomCollisionMask": true,
                  "image": "flatboy/png/Jump (4).png",
                  "points": [],
                  "originPoint": {
                    "name": "origine",
                    "x": 2.5,
                    "y": -1
                  },
                  "centerPoint": {
                    "automatic": false,
                    "name": "centre",
                    "x": 143.281,
                    "y": 337.5
                  },
                  "customCollisionMask": []
                },
                {
                  "hasCustomCollisionMask": true,
                  "image": "flatboy/png/Jump (5).png",
                  "points": [],
                  "originPoint": {
                    "name": "origine",
                    "x": 2.5,
                    "y": -1
                  },
                  "centerPoint": {
                    "automatic": false,
                    "name": "centre",
                    "x": 143.281,
                    "y": 337.5
                  },
                  "customCollisionMask": []
                },
                {
                  "hasCustomCollisionMask": true,
                  "image": "flatboy/png/Jump (6).png",
                  "points": [],
                  "originPoint": {
                    "name": "origine",
                    "x": 2.5,
                    "y": -1
                  },
                  "centerPoint": {
                    "automatic": false,
                    "name": "centre",
                    "x": 143.281,
                    "y": 337.5
                  },
                  "customCollisionMask": []
                },
                {
                  "hasCustomCollisionMask": true,
                  "image": "flatboy/png/Jump (7).png",
                  "points": [],
                  "originPoint": {
                    "name": "origine",
                    "x": 2.5,
                    "y": -1
                  },
                  "centerPoint": {
                    "automatic": false,
                    "name": "centre",
                    "x": 143.281,
                    "y": 337.5
                  },
                  "customCollisionMask": []
                },
                {
                  "hasCustomCollisionMask": true,
                  "image": "flatboy/png/Jump (8).png",
                  "points": [],
                  "originPoint": {
                    "name": "origine",
                    "x": 2.5,
                    "y": -1
                  },
                  "centerPoint": {
                    "automatic": false,
                    "name": "centre",
                    "x": 143.281,
                    "y": 337.5
                  },
                  "customCollisionMask": []
                },
                {
                  "hasCustomCollisionMask": true,
                  "image": "flatboy/png/Jump (9).png",
                  "points": [],
                  "originPoint": {
                    "name": "origine",
                    "x": 2.5,
                    "y": -1
                  },
                  "centerPoint": {
                    "automatic": false,
                    "name": "centre",
                    "x": 143.281,
                    "y": 337.5
                  },
                  "customCollisionMask": []
                },
                {
                  "hasCustomCollisionMask": true,
                  "image": "flatboy/png/Jump (10).png",
                  "points": [],
                  "originPoint": {
                    "name": "origine",
                    "x": 2.5,
                    "y": -1
                  },
                  "centerPoint": {
                    "automatic": false,
                    "name": "centre",
                    "x": 143.281,
                    "y": 337.5
                  },
                  "customCollisionMask": []
                },
                {
                  "hasCustomCollisionMask": true,
                  "image": "flatboy/png/Jump (11).png",
                  "points": [],
                  "originPoint": {
                    "name": "origine",
                    "x": 2.5,
                    "y": -1
                  },
                  "centerPoint": {
                    "automatic": false,
                    "name": "centre",
                    "x": 143.281,
                    "y": 337.5
                  },
                  "customCollisionMask": []
                },
                {
                  "hasCustomCollisionMask": true,
                  "image": "flatboy/png/Jump (12).png",
                  "points": [],
                  "originPoint": {
                    "name": "origine",
                    "x": 2.5,
                    "y": -1
                  },
                  "centerPoint": {
                    "automatic": false,
                    "name": "centre",
                    "x": 143.281,
                    "y": 337.5
                  },
                  "customCollisionMask": []
                },
                {
                  "hasCustomCollisionMask": true,
                  "image": "flatboy/png/Jump (13).png",
                  "points": [],
                  "originPoint": {
                    "name": "origine",
                    "x": 2.5,
                    "y": -1
                  },
                  "centerPoint": {
                    "automatic": false,
                    "name": "centre",
                    "x": 143.281,
                    "y": 337.5
                  },
                  "customCollisionMask": []
                },
                {
                  "hasCustomCollisionMask": true,
                  "image": "flatboy/png/Jump (14).png",
                  "points": [],
                  "originPoint": {
                    "name": "origine",
                    "x": 2.5,
                    "y": -1
                  },
                  "centerPoint": {
                    "automatic": false,
                    "name": "centre",
                    "x": 143.281,
                    "y": 337.5
                  },
                  "customCollisionMask": []
                },
                {
                  "hasCustomCollisionMask": true,
                  "image": "flatboy/png/Jump (15).png",
                  "points": [],
                  "originPoint": {
                    "name": "origine",
                    "x": 2.5,
                    "y": -1
                  },
                  "centerPoint": {
                    "automatic": false,
                    "name": "centre",
                    "x": 143.281,
                    "y": 337.5
                  },
                  "customCollisionMask": []
                }
              ]
            }
          ]
        },
        {
          "name": "running",
          "useMultipleDirections": false,
          "directions": [
            {
              "looping": true,
              "timeBetweenFrames": 0.08,
              "sprites": [
                {
                  "hasCustomCollisionMask": true,
                  "image": "flatboy/png/Run (1).png",
                  "points": [],
                  "originPoint": {
                    "name": "origine",
                    "x": 2.5,
                    "y": -1
                  },
                  "centerPoint": {
                    "automatic": false,
                    "name": "centre",
                    "x": 143.281,
                    "y": 337.5
                  },
                  "customCollisionMask": []
                },
                {
                  "hasCustomCollisionMask": true,
                  "image": "flatboy/png/Run (2).png",
                  "points": [],
                  "originPoint": {
                    "name": "origine",
                    "x": 2.5,
                    "y": -1
                  },
                  "centerPoint": {
                    "automatic": false,
                    "name": "centre",
                    "x": 143.281,
                    "y": 337.5
                  },
                  "customCollisionMask": []
                },
                {
                  "hasCustomCollisionMask": true,
                  "image": "flatboy/png/Run (3).png",
                  "points": [],
                  "originPoint": {
                    "name": "origine",
                    "x": 2.5,
                    "y": -1
                  },
                  "centerPoint": {
                    "automatic": false,
                    "name": "centre",
                    "x": 143.281,
                    "y": 337.5
                  },
                  "customCollisionMask": []
                },
                {
                  "hasCustomCollisionMask": true,
                  "image": "flatboy/png/Run (4).png",
                  "points": [],
                  "originPoint": {
                    "name": "origine",
                    "x": 2.5,
                    "y": -1
                  },
                  "centerPoint": {
                    "automatic": false,
                    "name": "centre",
                    "x": 143.281,
                    "y": 337.5
                  },
                  "customCollisionMask": []
                },
                {
                  "hasCustomCollisionMask": true,
                  "image": "flatboy/png/Run (5).png",
                  "points": [],
                  "originPoint": {
                    "name": "origine",
                    "x": 2.5,
                    "y": -1
                  },
                  "centerPoint": {
                    "automatic": false,
                    "name": "centre",
                    "x": 143.281,
                    "y": 337.5
                  },
                  "customCollisionMask": []
                },
                {
                  "hasCustomCollisionMask": true,
                  "image": "flatboy/png/Run (6).png",
                  "points": [],
                  "originPoint": {
                    "name": "origine",
                    "x": 2.5,
                    "y": -1
                  },
                  "centerPoint": {
                    "automatic": false,
                    "name": "centre",
                    "x": 143.281,
                    "y": 337.5
                  },
                  "customCollisionMask": []
                },
                {
                  "hasCustomCollisionMask": true,
                  "image": "flatboy/png/Run (7).png",
                  "points": [],
                  "originPoint": {
                    "name": "origine",
                    "x": 2.5,
                    "y": -1
                  },
                  "centerPoint": {
                    "automatic": false,
                    "name": "centre",
                    "x": 143.281,
                    "y": 337.5
                  },
                  "customCollisionMask": []
                },
                {
                  "hasCustomCollisionMask": true,
                  "image": "flatboy/png/Run (8).png",
                  "points": [],
                  "originPoint": {
                    "name": "origine",
                    "x": 2.5,
                    "y": -1
                  },
                  "centerPoint": {
                    "automatic": false,
                    "name": "centre",
                    "x": 143.281,
                    "y": 337.5
                  },
                  "customCollisionMask": []
                },
                {
                  "hasCustomCollisionMask": true,
                  "image": "flatboy/png/Run (9).png",
                  "points": [],
                  "originPoint": {
                    "name": "origine",
                    "x": 2.5,
                    "y": -1
                  },
                  "centerPoint": {
                    "automatic": false,
                    "name": "centre",
                    "x": 143.281,
                    "y": 337.5
                  },
                  "customCollisionMask": []
                },
                {
                  "hasCustomCollisionMask": true,
                  "image": "flatboy/png/Run (10).png",
                  "points": [],
                  "originPoint": {
                    "name": "origine",
                    "x": 2.5,
                    "y": -1
                  },
                  "centerPoint": {
                    "automatic": false,
                    "name": "centre",
                    "x": 143.281,
                    "y": 337.5
                  },
                  "customCollisionMask": []
                },
                {
                  "hasCustomCollisionMask": true,
                  "image": "flatboy/png/Run (11).png",
                  "points": [],
                  "originPoint": {
                    "name": "origine",
                    "x": 2.5,
                    "y": -1
                  },
                  "centerPoint": {
                    "automatic": false,
                    "name": "centre",
                    "x": 143.281,
                    "y": 337.5
                  },
                  "customCollisionMask": []
                },
                {
                  "hasCustomCollisionMask": true,
                  "image": "flatboy/png/Run (12).png",
                  "points": [],
                  "originPoint": {
                    "name": "origine",
                    "x": 2.5,
                    "y": -1
                  },
                  "centerPoint": {
                    "automatic": false,
                    "name": "centre",
                    "x": 143.281,
                    "y": 337.5
                  },
                  "customCollisionMask": []
                },
                {
                  "hasCustomCollisionMask": true,
                  "image": "flatboy/png/Run (13).png",
                  "points": [],
                  "originPoint": {
                    "name": "origine",
                    "x": 2.5,
                    "y": -1
                  },
                  "centerPoint": {
                    "automatic": false,
                    "name": "centre",
                    "x": 143.281,
                    "y": 337.5
                  },
                  "customCollisionMask": []
                },
                {
                  "hasCustomCollisionMask": true,
                  "image": "flatboy/png/Run (14).png",
                  "points": [],
                  "originPoint": {
                    "name": "origine",
                    "x": 2.5,
                    "y": -1
                  },
                  "centerPoint": {
                    "automatic": false,
                    "name": "centre",
                    "x": 143.281,
                    "y": 337.5
                  },
                  "customCollisionMask": []
                },
                {
                  "hasCustomCollisionMask": true,
                  "image": "flatboy/png/Run (15).png",
                  "points": [],
                  "originPoint": {
                    "name": "origine",
                    "x": 2.5,
                    "y": -1
                  },
                  "centerPoint": {
                    "automatic": false,
                    "name": "centre",
                    "x": 143.281,
                    "y": 337.5
                  },
                  "customCollisionMask": []
                }
              ]
            }
          ]
        },
        {
          "name": "walk",
          "useMultipleDirections": false,
          "directions": [
            {
              "looping": true,
              "timeBetweenFrames": 0.08,
              "sprites": [
                {
                  "hasCustomCollisionMask": true,
                  "image": "flatboy/png/Walk (1).png",
                  "points": [],
                  "originPoint": {
                    "name": "origine",
                    "x": 2.5,
                    "y": -1
                  },
                  "centerPoint": {
                    "automatic": false,
                    "name": "centre",
                    "x": 143.281,
                    "y": 337.5
                  },
                  "customCollisionMask": []
                },
                {
                  "hasCustomCollisionMask": true,
                  "image": "flatboy/png/Walk (2).png",
                  "points": [],
                  "originPoint": {
                    "name": "origine",
                    "x": 2.5,
                    "y": -1
                  },
                  "centerPoint": {
                    "automatic": false,
                    "name": "centre",
                    "x": 143.281,
                    "y": 337.5
                  },
                  "customCollisionMask": []
                },
                {
                  "hasCustomCollisionMask": true,
                  "image": "flatboy/png/Walk (3).png",
                  "points": [],
                  "originPoint": {
                    "name": "origine",
                    "x": 2.5,
                    "y": -1
                  },
                  "centerPoint": {
                    "automatic": false,
                    "name": "centre",
                    "x": 143.281,
                    "y": 337.5
                  },
                  "customCollisionMask": []
                },
                {
                  "hasCustomCollisionMask": true,
                  "image": "flatboy/png/Walk (4).png",
                  "points": [],
                  "originPoint": {
                    "name": "origine",
                    "x": 2.5,
                    "y": -1
                  },
                  "centerPoint": {
                    "automatic": false,
                    "name": "centre",
                    "x": 143.281,
                    "y": 337.5
                  },
                  "customCollisionMask": []
                },
                {
                  "hasCustomCollisionMask": true,
                  "image": "flatboy/png/Walk (5).png",
                  "points": [],
                  "originPoint": {
                    "name": "origine",
                    "x": 2.5,
                    "y": -1
                  },
                  "centerPoint": {
                    "automatic": false,
                    "name": "centre",
                    "x": 143.281,
                    "y": 337.5
                  },
                  "customCollisionMask": []
                },
                {
                  "hasCustomCollisionMask": true,
                  "image": "flatboy/png/Walk (6).png",
                  "points": [],
                  "originPoint": {
                    "name": "origine",
                    "x": 2.5,
                    "y": -1
                  },
                  "centerPoint": {
                    "automatic": false,
                    "name": "centre",
                    "x": 143.281,
                    "y": 337.5
                  },
                  "customCollisionMask": []
                },
                {
                  "hasCustomCollisionMask": true,
                  "image": "flatboy/png/Walk (7).png",
                  "points": [],
                  "originPoint": {
                    "name": "origine",
                    "x": 2.5,
                    "y": -1
                  },
                  "centerPoint": {
                    "automatic": false,
                    "name": "centre",
                    "x": 143.281,
                    "y": 337.5
                  },
                  "customCollisionMask": []
                },
                {
                  "hasCustomCollisionMask": true,
                  "image": "flatboy/png/Walk (8).png",
                  "points": [],
                  "originPoint": {
                    "name": "origine",
                    "x": 2.5,
                    "y": -1
                  },
                  "centerPoint": {
                    "automatic": false,
                    "name": "centre",
                    "x": 143.281,
                    "y": 337.5
                  },
                  "customCollisionMask": []
                },
                {
                  "hasCustomCollisionMask": true,
                  "image": "flatboy/png/Walk (9).png",
                  "points": [],
                  "originPoint": {
                    "name": "origine",
                    "x": 2.5,
                    "y": -1
                  },
                  "centerPoint": {
                    "automatic": false,
                    "name": "centre",
                    "x": 143.281,
                    "y": 337.5
                  },
                  "customCollisionMask": []
                },
                {
                  "hasCustomCollisionMask": true,
                  "image": "flatboy/png/Walk (10).png",
                  "points": [],
                  "originPoint": {
                    "name": "origine",
                    "x": 2.5,
                    "y": -1
                  },
                  "centerPoint": {
                    "automatic": false,
                    "name": "centre",
                    "x": 143.281,
                    "y": 337.5
                  },
                  "customCollisionMask": []
                },
                {
                  "hasCustomCollisionMask": true,
                  "image": "flatboy/png/Walk (11).png",
                  "points": [],
                  "originPoint": {
                    "name": "origine",
                    "x": 2.5,
                    "y": -1
                  },
                  "centerPoint": {
                    "automatic": false,
                    "name": "centre",
                    "x": 143.281,
                    "y": 337.5
                  },
                  "customCollisionMask": []
                },
                {
                  "hasCustomCollisionMask": true,
                  "image": "flatboy/png/Walk (12).png",
                  "points": [],
                  "originPoint": {
                    "name": "origine",
                    "x": 2.5,
                    "y": -1
                  },
                  "centerPoint": {
                    "automatic": false,
                    "name": "centre",
                    "x": 143.281,
                    "y": 337.5
                  },
                  "customCollisionMask": []
                },
                {
                  "hasCustomCollisionMask": true,
                  "image": "flatboy/png/Walk (13).png",
                  "points": [],
                  "originPoint": {
                    "name": "origine",
                    "x": 2.5,
                    "y": -1
                  },
                  "centerPoint": {
                    "automatic": false,
                    "name": "centre",
                    "x": 143.281,
                    "y": 337.5
                  },
                  "customCollisionMask": []
                },
                {
                  "hasCustomCollisionMask": true,
                  "image": "flatboy/png/Walk (14).png",
                  "points": [],
                  "originPoint": {
                    "name": "origine",
                    "x": 2.5,
                    "y": -1
                  },
                  "centerPoint": {
                    "automatic": false,
                    "name": "centre",
                    "x": 143.281,
                    "y": 337.5
                  },
                  "customCollisionMask": []
                },
                {
                  "hasCustomCollisionMask": true,
                  "image": "flatboy/png/Walk (15).png",
                  "points": [],
                  "originPoint": {
                    "name": "origine",
                    "x": 2.5,
                    "y": -1
                  },
                  "centerPoint": {
                    "automatic": false,
                    "name": "centre",
                    "x": 143.281,
                    "y": 337.5
                  },
                  "customCollisionMask": []
                }
              ]
            }
          ]
        }
      ]
    },
    {
      "height": 32,
      "name": "Platform",
      "tags": "",
      "texture": "bridge.png",
      "type": "TiledSpriteObject::TiledSprite",
      "width": 32,
      "variables": [],
      "behaviors": [
        {
          "name": "Platform",
          "type": "PlatformBehavior::PlatformBehavior",
          "canBeGrabbed": true,
          "platformType": "NormalPlatform",
          "yGrabOffset": 0
        }
      ]
    },
    {
      "name": "NewObject",
      "tags": "",
      "type": "Sprite",
      "updateIfNotVisible": false,
      "variables": [],
      "behaviors": [],
      "animations": [
        {
          "name": "",
          "useMultipleDirections": false,
          "directions": [
            {
              "looping": false,
              "timeBetweenFrames": 0.08,
              "sprites": [
                {
                  "hasCustomCollisionMask": false,
                  "image": "freetileset/png/Tiles/SurfaceMiddle.png",
                  "points": [],
                  "originPoint": {
                    "name": "origine",
                    "x": 0,
                    "y": 0
                  },
                  "centerPoint": {
                    "automatic": true,
                    "name": "centre",
                    "x": 0,
                    "y": 0
                  },
                  "customCollisionMask": []
                }
              ]
            }
          ]
        }
      ]
    },
    {
      "name": "NewObject2",
      "tags": "",
      "type": "Sprite",
      "updateIfNotVisible": false,
      "variables": [],
      "behaviors": [],
      "animations": []
    },
    {
      "height": 32,
      "name": "Background",
      "tags": "",
      "texture": "freetileset/png/BG/BG-1.png",
      "type": "TiledSpriteObject::TiledSprite",
      "width": 32,
      "variables": [],
      "behaviors": []
    },
    {
      "height": 32,
      "name": "SquareSurface",
      "tags": "",
      "texture": "freetileset/png/Tiles/SurfaceMiddle.png",
      "type": "TiledSpriteObject::TiledSprite",
      "width": 32,
      "variables": [],
      "behaviors": [
        {
          "canBeGrabbed": false,
          "name": "Platform",
          "platformType": "NormalPlatform",
          "type": "PlatformBehavior::PlatformBehavior",
          "yGrabOffset": 0
        }
      ]
    },
    {
      "name": "LeftCliff",
      "tags": "",
      "type": "Sprite",
      "updateIfNotVisible": false,
      "variables": [],
      "behaviors": [
        {
          "canBeGrabbed": false,
          "name": "Platform",
          "platformType": "NormalPlatform",
          "type": "PlatformBehavior::PlatformBehavior",
          "yGrabOffset": 0
        }
      ],
      "animations": [
        {
          "name": "",
          "useMultipleDirections": false,
          "directions": [
            {
              "looping": false,
              "timeBetweenFrames": 0.08,
              "sprites": [
                {
                  "hasCustomCollisionMask": true,
                  "image": "freetileset/png/Tiles/CliffLeft.png",
                  "points": [],
                  "originPoint": {
                    "name": "origine",
                    "x": 0,
                    "y": 0
                  },
                  "centerPoint": {
                    "automatic": true,
                    "name": "centre",
                    "x": 0,
                    "y": 0
                  },
                  "customCollisionMask": [
                    [
                      {
                        "x": 127.5,
                        "y": 91
                      },
                      {
                        "x": 73.5,
                        "y": 83
                      },
                      {
                        "x": 44.5,
                        "y": 56
                      },
                      {
                        "x": 7.5,
                        "y": 46
                      },
                      {
                        "x": 1.5,
                        "y": 1
                      },
                      {
                        "x": 127.5,
                        "y": 1
                      }
                    ]
                  ]
                }
              ]
            }
          ]
        }
      ]
    },
    {
      "height": 32,
      "name": "OceanSurface",
      "tags": "",
      "texture": "freetileset/png/Tiles/WaterSurface.png",
      "type": "TiledSpriteObject::TiledSprite",
      "width": 32,
      "variables": [],
      "behaviors": []
    },
    {
      "height": 32,
      "name": "RightCurveSurface",
      "tags": "",
      "texture": "freetileset/png/Tiles/SurfaceRightCurve.png",
      "type": "TiledSpriteObject::TiledSprite",
      "width": 32,
      "variables": [],
      "behaviors": [
        {
          "canBeGrabbed": true,
          "name": "Platform",
          "platformType": "NormalPlatform",
          "type": "PlatformBehavior::PlatformBehavior",
          "yGrabOffset": 0
        }
      ]
    },
    {
      "name": "NewObject5",
      "tags": "",
      "type": "Sprite",
      "updateIfNotVisible": false,
      "variables": [],
      "behaviors": [
        {
          "canBeGrabbed": true,
          "name": "Platform",
          "platformType": "NormalPlatform",
          "type": "PlatformBehavior::PlatformBehavior",
          "yGrabOffset": 0
        }
      ],
      "animations": [
        {
          "name": "",
          "useMultipleDirections": false,
          "directions": [
            {
              "looping": false,
              "timeBetweenFrames": 0.08,
              "sprites": [
                {
                  "hasCustomCollisionMask": false,
                  "image": "freetileset/png/Tiles/SurfaceLeftCrumble.png",
                  "points": [],
                  "originPoint": {
                    "name": "origine",
                    "x": 0,
                    "y": 0
                  },
                  "centerPoint": {
                    "automatic": true,
                    "name": "centre",
                    "x": 0,
                    "y": 0
                  },
                  "customCollisionMask": []
                }
              ]
            }
          ]
        }
      ]
    },
    {
      "height": 32,
      "name": "NewObject6",
      "tags": "",
      "texture": "freetileset/png/Tiles/SoilLeft.png",
      "type": "TiledSpriteObject::TiledSprite",
      "width": 32,
      "variables": [],
      "behaviors": [
        {
          "canBeGrabbed": true,
          "name": "Platform",
          "platformType": "NormalPlatform",
          "type": "PlatformBehavior::PlatformBehavior",
          "yGrabOffset": 0
        }
      ]
    },
    {
      "height": 32,
      "name": "NewObject7",
      "tags": "",
      "texture": "freetileset/png/Tiles/SoilMiddle.png",
      "type": "TiledSpriteObject::TiledSprite",
      "width": 32,
      "variables": [],
      "behaviors": [
        {
          "canBeGrabbed": true,
          "name": "Platform",
          "platformType": "NormalPlatform",
          "type": "PlatformBehavior::PlatformBehavior",
          "yGrabOffset": 0
        }
      ]
    },
    {
      "height": 32,
      "name": "NewObject8",
      "tags": "",
      "texture": "freetileset/png/Tiles/SurfaceMiddle.png",
      "type": "TiledSpriteObject::TiledSprite",
      "width": 32,
      "variables": [],
      "behaviors": [
        {
          "canBeGrabbed": true,
          "name": "Platform",
          "platformType": "NormalPlatform",
          "type": "PlatformBehavior::PlatformBehavior",
          "yGrabOffset": 0
        }
      ]
    },
    {
      "height": 32,
      "name": "SurfaceLeftCurve",
      "tags": "",
      "texture": "freetileset/png/Tiles/SurfaceLeftCurve.png",
      "type": "TiledSpriteObject::TiledSprite",
      "width": 32,
      "variables": [],
      "behaviors": [
        {
          "canBeGrabbed": true,
          "name": "Platform",
          "platformType": "NormalPlatform",
          "type": "PlatformBehavior::PlatformBehavior",
          "yGrabOffset": 0
        }
      ]
    },
    {
      "height": 32,
      "name": "SoilRight",
      "tags": "",
      "texture": "freetileset/png/Tiles/SoilRight.png",
      "type": "TiledSpriteObject::TiledSprite",
      "width": 32,
      "variables": [],
      "behaviors": [
        {
          "canBeGrabbed": true,
          "name": "Platform",
          "platformType": "NormalPlatform",
          "type": "PlatformBehavior::PlatformBehavior",
          "yGrabOffset": 0
        }
      ]
    },
    {
      "height": 32,
      "name": "SurfaceRightCrumble",
      "tags": "",
      "texture": "freetileset/png/Tiles/SurfaceRightCrumble.png",
      "type": "TiledSpriteObject::TiledSprite",
      "width": 32,
      "variables": [],
      "behaviors": [
        {
          "canBeGrabbed": true,
          "name": "Platform",
          "platformType": "NormalPlatform",
          "type": "PlatformBehavior::PlatformBehavior",
          "yGrabOffset": 0
        }
      ]
    },
    {
      "name": "PlayerHitBox",
      "tags": "",
      "type": "Sprite",
      "updateIfNotVisible": false,
      "variables": [],
      "behaviors": [
        {
          "acceleration": 1500,
          "canGrabPlatforms": false,
          "deceleration": 1500,
          "gravity": 1000,
          "ignoreDefaultControls": false,
          "jumpSpeed": 600,
          "maxFallingSpeed": 700,
          "maxSpeed": 250,
          "name": "PlatformerObject",
          "roundCoordinates": true,
          "slopeMaxAngle": 60,
          "type": "PlatformBehavior::PlatformerObjectBehavior",
          "xGrabTolerance": 10,
          "yGrabOffset": 0
        },
        {
          "name": "Tween",
          "type": "Tween::TweenBehavior"
        }
      ],
      "animations": [
        {
          "name": "",
          "useMultipleDirections": false,
          "directions": [
            {
              "looping": false,
              "timeBetweenFrames": 1,
              "sprites": [
                {
                  "hasCustomCollisionMask": false,
                  "image": "PlayerArea.png",
                  "points": [],
                  "originPoint": {
                    "name": "origine",
                    "x": 0,
                    "y": 0
                  },
                  "centerPoint": {
                    "automatic": true,
                    "name": "centre",
                    "x": 0,
                    "y": 0
                  },
                  "customCollisionMask": []
                }
              ]
            }
          ]
        }
      ]
    },
    {
      "name": "CliffRight",
      "tags": "",
      "type": "Sprite",
      "updateIfNotVisible": false,
      "variables": [],
      "behaviors": [
        {
          "canBeGrabbed": true,
          "name": "Platform",
          "platformType": "NormalPlatform",
          "type": "PlatformBehavior::PlatformBehavior",
          "yGrabOffset": 0
        }
      ],
      "animations": [
        {
          "name": "",
          "useMultipleDirections": false,
          "directions": [
            {
              "looping": false,
              "timeBetweenFrames": 0.08,
              "sprites": [
                {
                  "hasCustomCollisionMask": false,
                  "image": "freetileset/png/Tiles/CliffRight.png",
                  "points": [],
                  "originPoint": {
                    "name": "origine",
                    "x": 0,
                    "y": 0
                  },
                  "centerPoint": {
                    "automatic": true,
                    "name": "centre",
                    "x": 0,
                    "y": 0
                  },
                  "customCollisionMask": []
                }
              ]
            }
          ]
        }
      ]
    },
    {
      "name": "CliffMiddle",
      "tags": "",
      "type": "Sprite",
      "updateIfNotVisible": false,
      "variables": [],
      "behaviors": [
        {
          "canBeGrabbed": true,
          "name": "Platform",
          "platformType": "NormalPlatform",
          "type": "PlatformBehavior::PlatformBehavior",
          "yGrabOffset": 0
        }
      ],
      "animations": [
        {
          "name": "",
          "useMultipleDirections": false,
          "directions": [
            {
              "looping": false,
              "timeBetweenFrames": 0.08,
              "sprites": [
                {
                  "hasCustomCollisionMask": false,
                  "image": "freetileset/png/Tiles/SurfaceMiddleCrumble.png",
                  "points": [],
                  "originPoint": {
                    "name": "origine",
                    "x": 0,
                    "y": 0
                  },
                  "centerPoint": {
                    "automatic": true,
                    "name": "centre",
                    "x": 0,
                    "y": 0
                  },
                  "customCollisionMask": []
                }
              ]
            }
          ]
        }
      ]
    },
    {
      "name": "Box",
      "tags": "",
      "type": "Sprite",
      "updateIfNotVisible": false,
      "variables": [],
      "behaviors": [
        {
          "canBeGrabbed": true,
          "name": "Platform",
          "platformType": "NormalPlatform",
          "type": "PlatformBehavior::PlatformBehavior",
          "yGrabOffset": 0
        }
      ],
      "animations": [
        {
          "name": "",
          "useMultipleDirections": false,
          "directions": [
            {
              "looping": false,
              "timeBetweenFrames": 0.08,
              "sprites": [
                {
                  "hasCustomCollisionMask": false,
                  "image": "freetileset/png/Object/Crate.png",
                  "points": [],
                  "originPoint": {
                    "name": "origine",
                    "x": 0,
                    "y": 0
                  },
                  "centerPoint": {
                    "automatic": true,
                    "name": "centre",
                    "x": 0,
                    "y": 0
                  },
                  "customCollisionMask": []
                }
              ]
            }
          ]
        }
      ]
    },
    {
      "name": "water",
      "tags": "",
      "type": "Sprite",
      "updateIfNotVisible": false,
      "variables": [],
      "behaviors": [],
      "animations": [
        {
          "name": "",
          "useMultipleDirections": false,
          "directions": [
            {
              "looping": false,
              "timeBetweenFrames": 0.08,
              "sprites": [
                {
                  "hasCustomCollisionMask": false,
                  "image": "freetileset/png/Tiles/WaterDepth.png",
                  "points": [],
                  "originPoint": {
                    "name": "origine",
                    "x": 0,
                    "y": 0
                  },
                  "centerPoint": {
                    "automatic": true,
                    "name": "centre",
                    "x": 0,
                    "y": 0
                  },
                  "customCollisionMask": []
                }
              ]
            }
          ]
        }
      ]
    },
    {
      "name": "tree2",
      "tags": "",
      "type": "Sprite",
      "updateIfNotVisible": false,
      "variables": [],
      "behaviors": [],
      "animations": [
        {
          "name": "",
          "useMultipleDirections": false,
          "directions": [
            {
              "looping": false,
              "timeBetweenFrames": 0.08,
              "sprites": [
                {
                  "hasCustomCollisionMask": false,
                  "image": "freetileset/png/Object/Tree_2.png",
                  "points": [],
                  "originPoint": {
                    "name": "origine",
                    "x": 0,
                    "y": 0
                  },
                  "centerPoint": {
                    "automatic": true,
                    "name": "centre",
                    "x": 0,
                    "y": 0
                  },
                  "customCollisionMask": []
                }
              ]
            }
          ]
        }
      ]
    },
    {
      "name": "tree1",
      "tags": "",
      "type": "Sprite",
      "updateIfNotVisible": false,
      "variables": [],
      "behaviors": [
        {
          "canBeGrabbed": true,
          "name": "Platform",
          "platformType": "NormalPlatform",
          "type": "PlatformBehavior::PlatformBehavior",
          "yGrabOffset": 0
        }
      ],
      "animations": [
        {
          "name": "",
          "useMultipleDirections": false,
          "directions": [
            {
              "looping": false,
              "timeBetweenFrames": 0.08,
              "sprites": [
                {
                  "hasCustomCollisionMask": false,
                  "image": "freetileset/png/Object/Tree_1.png",
                  "points": [],
                  "originPoint": {
                    "name": "origine",
                    "x": 0,
                    "y": 0
                  },
                  "centerPoint": {
                    "automatic": true,
                    "name": "centre",
                    "x": 0,
                    "y": 0
                  },
                  "customCollisionMask": []
                }
              ]
            }
          ]
        }
      ]
    },
    {
      "name": "tree3",
      "tags": "",
      "type": "Sprite",
      "updateIfNotVisible": false,
      "variables": [],
      "behaviors": [],
      "animations": [
        {
          "name": "",
          "useMultipleDirections": false,
          "directions": [
            {
              "looping": false,
              "timeBetweenFrames": 0.08,
              "sprites": [
                {
                  "hasCustomCollisionMask": false,
                  "image": "freetileset/png/Object/Tree_3.png",
                  "points": [],
                  "originPoint": {
                    "name": "origine",
                    "x": 0,
                    "y": 0
                  },
                  "centerPoint": {
                    "automatic": true,
                    "name": "centre",
                    "x": 0,
                    "y": 0
                  },
                  "customCollisionMask": []
                }
              ]
            }
          ]
        }
      ]
    },
    {
      "name": "stone",
      "tags": "",
      "type": "Sprite",
      "updateIfNotVisible": false,
      "variables": [],
      "behaviors": [],
      "animations": [
        {
          "name": "",
          "useMultipleDirections": false,
          "directions": [
            {
              "looping": false,
              "timeBetweenFrames": 0.08,
              "sprites": [
                {
                  "hasCustomCollisionMask": false,
                  "image": "freetileset/png/Object/Stone.png",
                  "points": [],
                  "originPoint": {
                    "name": "origine",
                    "x": 0,
                    "y": 0
                  },
                  "centerPoint": {
                    "automatic": true,
                    "name": "centre",
                    "x": 0,
                    "y": 0
                  },
                  "customCollisionMask": []
                }
              ]
            }
          ]
        }
      ]
    },
    {
      "name": "mushroom1",
      "tags": "",
      "type": "Sprite",
      "updateIfNotVisible": false,
      "variables": [],
      "behaviors": [],
      "animations": [
        {
          "name": "",
          "useMultipleDirections": false,
          "directions": [
            {
              "looping": false,
              "timeBetweenFrames": 0.08,
              "sprites": [
                {
                  "hasCustomCollisionMask": false,
                  "image": "freetileset/png/Object/Mushroom_1.png",
                  "points": [],
                  "originPoint": {
                    "name": "origine",
                    "x": 0,
                    "y": 0
                  },
                  "centerPoint": {
                    "automatic": true,
                    "name": "centre",
                    "x": 0,
                    "y": 0
                  },
                  "customCollisionMask": []
                }
              ]
            }
          ]
        }
      ]
    },
    {
      "name": "mushroom2",
      "tags": "",
      "type": "Sprite",
      "updateIfNotVisible": false,
      "variables": [],
      "behaviors": [],
      "animations": [
        {
          "name": "",
          "useMultipleDirections": false,
          "directions": [
            {
              "looping": false,
              "timeBetweenFrames": 0.08,
              "sprites": [
                {
                  "hasCustomCollisionMask": false,
                  "image": "freetileset/png/Object/Mushroom_2.png",
                  "points": [],
                  "originPoint": {
                    "name": "origine",
                    "x": 0,
                    "y": 0
                  },
                  "centerPoint": {
                    "automatic": true,
                    "name": "centre",
                    "x": 0,
                    "y": 0
                  },
                  "customCollisionMask": []
                }
              ]
            }
          ]
        }
      ]
    },
    {
      "name": "bush1",
      "tags": "",
      "type": "Sprite",
      "updateIfNotVisible": false,
      "variables": [],
      "behaviors": [],
      "animations": [
        {
          "name": "",
          "useMultipleDirections": false,
          "directions": [
            {
              "looping": false,
              "timeBetweenFrames": 0.08,
              "sprites": [
                {
                  "hasCustomCollisionMask": false,
                  "image": "freetileset/png/Object/Bush (1).png",
                  "points": [],
                  "originPoint": {
                    "name": "origine",
                    "x": 0,
                    "y": 0
                  },
                  "centerPoint": {
                    "automatic": true,
                    "name": "centre",
                    "x": 0,
                    "y": 0
                  },
                  "customCollisionMask": []
                }
              ]
            }
          ]
        }
      ]
    },
    {
      "name": "bush2",
      "tags": "",
      "type": "Sprite",
      "updateIfNotVisible": false,
      "variables": [],
      "behaviors": [],
      "animations": [
        {
          "name": "",
          "useMultipleDirections": false,
          "directions": [
            {
              "looping": false,
              "timeBetweenFrames": 0.08,
              "sprites": [
                {
                  "hasCustomCollisionMask": false,
                  "image": "freetileset/png/Object/Bush (2).png",
                  "points": [],
                  "originPoint": {
                    "name": "origine",
                    "x": 0,
                    "y": 0
                  },
                  "centerPoint": {
                    "automatic": true,
                    "name": "centre",
                    "x": 0,
                    "y": 0
                  },
                  "customCollisionMask": []
                }
              ]
            }
          ]
        }
      ]
    },
    {
      "name": "bush3",
      "tags": "",
      "type": "Sprite",
      "updateIfNotVisible": false,
      "variables": [],
      "behaviors": [],
      "animations": [
        {
          "name": "",
          "useMultipleDirections": false,
          "directions": [
            {
              "looping": false,
              "timeBetweenFrames": 0.08,
              "sprites": [
                {
                  "hasCustomCollisionMask": false,
                  "image": "freetileset/png/Object/Bush (3).png",
                  "points": [],
                  "originPoint": {
                    "name": "origine",
                    "x": 0,
                    "y": 0
                  },
                  "centerPoint": {
                    "automatic": true,
                    "name": "centre",
                    "x": 0,
                    "y": 0
                  },
                  "customCollisionMask": []
                }
              ]
            }
          ]
        }
      ]
    },
    {
      "name": "bush4",
      "tags": "",
      "type": "Sprite",
      "updateIfNotVisible": false,
      "variables": [],
      "behaviors": [],
      "animations": [
        {
          "name": "",
          "useMultipleDirections": false,
          "directions": [
            {
              "looping": false,
              "timeBetweenFrames": 0.08,
              "sprites": [
                {
                  "hasCustomCollisionMask": false,
                  "image": "freetileset/png/Object/Bush (4).png",
                  "points": [],
                  "originPoint": {
                    "name": "origine",
                    "x": 0,
                    "y": 0
                  },
                  "centerPoint": {
                    "automatic": true,
                    "name": "centre",
                    "x": 0,
                    "y": 0
                  },
                  "customCollisionMask": []
                }
              ]
            }
          ]
        }
      ]
    },
    {
      "height": 32,
      "name": "Ladder",
      "tags": "",
      "texture": "ladder_mid.png",
      "type": "TiledSpriteObject::TiledSprite",
      "width": 32,
      "variables": [],
      "behaviors": []
    }
  ],
  "events": [
    {
      "disabled": false,
      "folded": false,
      "type": "BuiltinCommonInstructions::Standard",
      "conditions": [],
      "actions": [
        {
          "type": {
            "inverted": false,
            "value": "MettreXY"
          },
          "parameters": [
            "Player",
            "=",
            "PlayerHitBox.X()-5",
            "=",
            "PlayerHitBox.Y()+3"
          ],
          "subInstructions": []
        }
      ],
      "events": []
    },
    {
      "disabled": false,
      "folded": false,
      "type": "BuiltinCommonInstructions::Standard",
      "conditions": [
        {
          "type": {
            "inverted": false,
            "value": "PlatformBehavior::IsJumping"
          },
          "parameters": [
            "PlayerHitBox",
            "PlatformerObject"
          ],
          "subInstructions": []
        }
      ],
      "actions": [
        {
          "type": {
            "inverted": false,
            "value": "SetAnimationName"
          },
          "parameters": [
            "Player",
            "\"jumping\""
          ],
          "subInstructions": []
        }
      ],
      "events": []
    },
    {
      "disabled": false,
      "folded": false,
      "type": "BuiltinCommonInstructions::Standard",
      "conditions": [
        {
          "type": {
            "inverted": false,
            "value": "PlatformBehavior::IsOnFloor"
          },
          "parameters": [
            "PlayerHitBox",
            "PlatformerObject"
          ],
          "subInstructions": []
        }
      ],
      "actions": [],
      "events": [
        {
          "disabled": false,
          "folded": false,
          "type": "BuiltinCommonInstructions::Standard",
          "conditions": [
            {
              "type": {
                "inverted": false,
                "value": "PlatformBehavior::IsMoving"
              },
              "parameters": [
                "PlayerHitBox",
                "PlatformerObject"
              ],
              "subInstructions": []
            }
          ],
          "actions": [
            {
              "type": {
                "inverted": false,
                "value": "SetAnimationName"
              },
              "parameters": [
                "Player",
                "\"running\""
              ],
              "subInstructions": []
            }
          ],
          "events": []
        },
        {
          "disabled": false,
          "folded": false,
          "type": "BuiltinCommonInstructions::Standard",
          "conditions": [
            {
              "type": {
                "inverted": true,
                "value": "PlatformBehavior::IsMoving"
              },
              "parameters": [
                "PlayerHitBox",
                "PlatformerObject"
              ],
              "subInstructions": []
            }
          ],
          "actions": [
            {
              "type": {
                "inverted": false,
                "value": "SetAnimationName"
              },
              "parameters": [
                "Player",
                "\"idle\""
              ],
              "subInstructions": []
            }
          ],
          "events": []
        }
      ]
    },
    {
      "disabled": false,
      "folded": false,
      "type": "BuiltinCommonInstructions::Standard",
      "conditions": [
        {
          "type": {
            "inverted": false,
            "value": "KeyPressed"
          },
          "parameters": [
            "",
            "Left"
          ],
          "subInstructions": []
        }
      ],
      "actions": [
        {
          "type": {
            "inverted": false,
            "value": "FlipX"
          },
          "parameters": [
            "Player",
            "yes"
          ],
          "subInstructions": []
        }
      ],
      "events": []
    },
    {
      "disabled": false,
      "folded": false,
      "type": "BuiltinCommonInstructions::Standard",
      "conditions": [
        {
          "type": {
            "inverted": false,
            "value": "KeyPressed"
          },
          "parameters": [
            "",
            "Right"
          ],
          "subInstructions": []
        }
      ],
      "actions": [
        {
          "type": {
            "inverted": false,
            "value": "FlipX"
          },
          "parameters": [
            "Player",
            "no"
          ],
          "subInstructions": []
        }
      ],
      "events": []
    },
    {
      "disabled": false,
      "folded": false,
      "type": "BuiltinCommonInstructions::Standard",
      "conditions": [],
      "actions": [
        {
          "type": {
            "inverted": false,
            "value": "CameraX"
          },
          "parameters": [
            "",
            "=",
            "Player.X()",
            "",
            ""
          ],
          "subInstructions": []
        }
      ],
      "events": []
    },
    {
      "disabled": false,
      "folded": false,
      "type": "BuiltinCommonInstructions::Standard",
      "conditions": [
        {
          "type": {
            "inverted": false,
            "value": "DepartScene"
          },
          "parameters": [
            ""
          ],
          "subInstructions": []
        }
      ],
      "actions": [],
      "events": []
    }
  ],
  "layers": [
    {
      "name": "",
      "visibility": true,
      "cameras": [
        {
          "defaultSize": true,
          "defaultViewport": true,
          "height": 0,
          "viewportBottom": 1,
          "viewportLeft": 0,
          "viewportRight": 1,
          "viewportTop": 0,
          "width": 0
        }
      ],
      "effects": []
    }
  ],
  "behaviorsSharedData": [
    {
      "name": "Platform",
      "type": "PlatformBehavior::PlatformBehavior"
    },
    {
      "name": "PlatformerObject",
      "type": "PlatformBehavior::PlatformerObjectBehavior"
    },
    {
      "name": "Tween",
      "type": "Tween::TweenBehavior"
    }
  ]
}